segscript/__init__.py
segscript/main.py
segscript/model.py
segscript/utils.py
segscript-0.1.7.dist-info/licenses/LICENSE
segscript-0.1.7.dist-info/METADATA
segscript-0.1.7.dist-info/WHEEL
segscript-0.1.7.dist-info/entry_points.txt
segscript-0.1.7.dist-info/top_level.txt
segscript-0.1.7.dist-info/RECORD
