Metadata-Version: 2.4
Name: segscript
Version: 0.1.7
Summary: Extract, refine, and analyze YouTube video segments with precision
License: Copyright 2025 SegScript
Project-URL: Homepage, https://github.com/keshavsharma25/SegScript
Project-URL: Repository, https://github.com/keshavsharma25/SegScript
Requires-Python: >=3.11
License-File: LICENSE
Requires-Dist: click
Requires-Dist: youtube-transcript-api
Requires-Dist: langchain-google-genai
Requires-Dist: python-dotenv
Requires-Dist: rich
Requires-Dist: requests
Requires-Dist: grpcio==1.60.1
Dynamic: license-file
